github_release_tool/__init__.py
github_release_tool/cli.py
github_release_tool/release.py
github_release_tool/version.py
github_release_tool-0.2.4.dist-info/entry_points.txt
github_release_tool-0.2.4.dist-info/LICENSE
github_release_tool-0.2.4.dist-info/WHEEL
github_release_tool-0.2.4.dist-info/METADATA
github_release_tool-0.2.4.dist-info/RECORD
