Metadata-Version: 2.1
Name: github_release_tool
Version: 0.2.4
Summary: Top-level package for github-release-tool.
Keywords: github api cli tool
Author-email: Matt Krueger <mkrueger@rstms.net>
Classifier: Intended Audience :: Developers
Classifier: Natural Language :: English
Classifier: Programming Language :: Python :: 3
Classifier: Programming Language :: Python :: 3.8
Classifier: Programming Language :: Python :: 3.9
Classifier: Programming Language :: Python :: 3.10
Requires-Dist: click
Requires-Dist: github3.py
Requires-Dist: black ; extra == "dev"
Requires-Dist: bump2version ; extra == "dev"
Requires-Dist: coverage ; extra == "dev"
Requires-Dist: flake8 ; extra == "dev"
Requires-Dist: pytest ; extra == "dev"
Requires-Dist: pdbpp ; extra == "dev"
Requires-Dist: python-box ; extra == "dev"
Requires-Dist: tox ; extra == "dev"
Requires-Dist: pytest-datadir ; extra == "dev"
Requires-Dist: sphinx ; extra == "docs"
Requires-Dist: sphinx-click ; extra == "docs"
Requires-Dist: sphinx-rtd-theme ; extra == "docs"
Project-URL: Home, https://github.com/rstms/github-release-tool
Provides-Extra: dev
Provides-Extra: docs
